pseudocode/__init__.py
pseudocode/__main__.py
pseudocode/cli.py
pseudocode/grammar/edexcel.bnf
pseudocode/main.py
pseudocode/tokens/__init__.py
pseudocode/tokens/cie.py
pseudocode/tokens/edexcel.py
pseudocode/transpilation/__init__.py
pseudocode/transpilation/ast.py
pseudocode/transpilation/bnf.py
pseudocode/transpilation/lexer.py
pseudocode/transpilation/parser.py
pseudocode/transpilation/transpile.py
pseudocode-0.0.1.dist-info/LICENSE
pseudocode-0.0.1.dist-info/METADATA
pseudocode-0.0.1.dist-info/WHEEL
pseudocode-0.0.1.dist-info/RECORD
