Metadata-Version: 2.3
Name: pseudocode
Version: 0.0.1
Summary: Run various pseudocode specifications.
License: LICENSE
Author: alternyxx
Author-email: alternyxx@gmail.com
Maintainer: alternyxx
Maintainer-email: alternyxx@gmail.com
Requires-Python: >=3.10
Classifier: License :: Other/Proprietary License
Classifier: Programming Language :: Python :: 3
Classifier: Programming Language :: Python :: 3.10
Classifier: Programming Language :: Python :: 3.11
Classifier: Programming Language :: Python :: 3.12
Classifier: Programming Language :: Python :: 3.13
